flight_display/__init__.py
flight_display/cli.py
flight_display/config.py
flight_display/tracker.py
flight_display-1.0.0.dist-info/METADATA
flight_display-1.0.0.dist-info/WHEEL
flight_display-1.0.0.dist-info/entry_points.txt
flight_display-1.0.0.dist-info/licenses/LICENSE
flight_display-1.0.0.dist-info/RECORD
