Metadata-Version: 2.4
Name: flight-display
Version: 1.0.0
Summary: Aircraft Tracker - Fully configurable airport departure board style display using ADS-B data
Project-URL: Homepage, https://github.com/rohankhatua/flight-display
Project-URL: Repository, https://github.com/rohankhatua/flight-display
Project-URL: Issues, https://github.com/rohankhatua/flight-display/issues
Author: Flight Display Team
License: MIT
License-File: LICENSE
Keywords: adsb,aircraft,aviation,configurable,departure-board,flight,radar,tracker
Classifier: Development Status :: 5 - Production/Stable
Classifier: Environment :: Console
Classifier: Intended Audience :: End Users/Desktop
Classifier: License :: OSI Approved :: MIT License
Classifier: Operating System :: OS Independent
Classifier: Programming Language :: Python :: 3
Classifier: Programming Language :: Python :: 3.8
Classifier: Programming Language :: Python :: 3.9
Classifier: Programming Language :: Python :: 3.10
Classifier: Programming Language :: Python :: 3.11
Classifier: Programming Language :: Python :: 3.12
Classifier: Programming Language :: Python :: 3.13
Classifier: Topic :: Scientific/Engineering :: Information Analysis
Classifier: Topic :: Utilities
Requires-Python: >=3.8
Requires-Dist: colorama>=0.4.6
Requires-Dist: requests>=2.32.4
Requires-Dist: tabulate>=0.9.0
